django_slots/__init__.py
django_slots/apps.py
django_slots/components.py
django_slots/models.py
django_slots/templatetags/__init__.py
django_slots/templatetags/slot_tags.py
django_slots/utils.py
django_slots-0.2.7.dist-info/WHEEL
django_slots-0.2.7.dist-info/METADATA
django_slots-0.2.7.dist-info/RECORD
