Metadata-Version: 2.1
Name: django-slots
Version: 0.2.7
Summary: django_slots = inclusion tag + blocks
Home-page: https://github.com/nwjlyons/django_slots
License: BSD-3-Clause
Keywords: slot,component,block,template,django
Author: Neil Lyons
Author-email: nwjlyons@googlemail.com
Requires-Python: >=3.10,<4.0
Classifier: License :: OSI Approved :: BSD License
Classifier: Programming Language :: Python :: 3
Classifier: Programming Language :: Python :: 3.10
Requires-Dist: Django (>=4.0.2,<5.0.0)
Project-URL: Repository, https://github.com/nwjlyons/django_slots
